setup.py
zevcrack.py
zevcrack.egg-info/PKG-INFO
zevcrack.egg-info/SOURCES.txt
zevcrack.egg-info/dependency_links.txt
zevcrack.egg-info/entry_points.txt
zevcrack.egg-info/not-zip-safe
zevcrack.egg-info/requires.txt
zevcrack.egg-info/top_level.txt