Metadata-Version: 1.1
Name: zevcrack
Version: 0.0.3
Summary: Advanced hash cracker
Home-page: https://github.com/zevtyardt/zevcrack
Author: noval wahyu ramadhan
Author-email: xnver404@gmail.com
License: MIT
Keywords: zevcrack
Platform: UNKNOWN
Classifier: Intended Audience :: Developers
Classifier: Natural Language :: English
Classifier: Programming Language :: Python :: 2
Classifier: Programming Language :: Python :: 2.7
